tootroll/__init__.py
tootroll/__main__.py
tootroll/accounts.py
tootroll/main.py
tootroll/oauth.py
tootroll/parquet.py
tootroll/py.typed
tootroll/timeline.py
tootroll/utils.py
tootroll/vars.py
tootroll-0.1.2.dist-info/LICENSE
tootroll-0.1.2.dist-info/WHEEL
tootroll-0.1.2.dist-info/METADATA
tootroll-0.1.2.dist-info/RECORD
