Metadata-Version: 2.1
Name: tootroll
Version: 0.1.2
Summary: Tootroll is a Python package to read timelines from the Mastodon network.
Author: Anthony Potappel
Author-email: anthonyp@lakeclub.net
Requires-Python: >=3.7,<4.0
Classifier: Programming Language :: Python :: 3
Classifier: Programming Language :: Python :: 3.7
Classifier: Programming Language :: Python :: 3.8
Classifier: Programming Language :: Python :: 3.9
Classifier: Programming Language :: Python :: 3.10
Requires-Dist: requests (>=2.28.1,<3.0.0)
